inspect_evals/__init__.py
inspect_evals/_registry.py
inspect_evals/hf_dataset_script_helper.py
inspect_evals/listing.yaml
inspect_evals/metadata.py
inspect_evals/py.typed
inspect_evals/utils.py
inspect_evals/abstention_bench/.gitignore
inspect_evals/abstention_bench/README.md
inspect_evals/abstention_bench/__init__.py
inspect_evals/abstention_bench/abstention_bench.py
inspect_evals/abstention_bench/utils.py
inspect_evals/abstention_bench/configs/default_pipeline.yaml
inspect_evals/abstention_bench/configs/dataset/alcuna.yaml
inspect_evals/abstention_bench/configs/dataset/bbq.yaml
inspect_evals/abstention_bench/configs/dataset/big_bench_disambiguate.yaml
inspect_evals/abstention_bench/configs/dataset/big_bench_known_unknowns.yaml
inspect_evals/abstention_bench/configs/dataset/coconot.yaml
inspect_evals/abstention_bench/configs/dataset/dummy.yaml
inspect_evals/abstention_bench/configs/dataset/falseqa.yaml
inspect_evals/abstention_bench/configs/dataset/freshqa.yaml
inspect_evals/abstention_bench/configs/dataset/gpqa.yaml
inspect_evals/abstention_bench/configs/dataset/gsm8k.yaml
inspect_evals/abstention_bench/configs/dataset/kuq.yaml
inspect_evals/abstention_bench/configs/dataset/mediq.yaml
inspect_evals/abstention_bench/configs/dataset/mmlu_history.yaml
inspect_evals/abstention_bench/configs/dataset/mmlu_math.yaml
inspect_evals/abstention_bench/configs/dataset/moralchoice.yaml
inspect_evals/abstention_bench/configs/dataset/musique.yaml
inspect_evals/abstention_bench/configs/dataset/qaqa.yaml
inspect_evals/abstention_bench/configs/dataset/qasper.yaml
inspect_evals/abstention_bench/configs/dataset/self_aware.yaml
inspect_evals/abstention_bench/configs/dataset/situated_qa.yaml
inspect_evals/abstention_bench/configs/dataset/squad2.yaml
inspect_evals/abstention_bench/configs/dataset/umwp.yaml
inspect_evals/abstention_bench/configs/dataset/worldsense.yaml
inspect_evals/abstention_bench/data/UMWP_indices_answerable.json
inspect_evals-0.3.102.dist-info/licenses/LICENSE
inspect_evals-0.3.102.dist-info/METADATA
inspect_evals-0.3.102.dist-info/WHEEL
inspect_evals-0.3.102.dist-info/entry_points.txt
inspect_evals-0.3.102.dist-info/top_level.txt
inspect_evals-0.3.102.dist-info/RECORD
